pyne_xmas_elves/client/__init__.py
pyne_xmas_elves/client/base.py
pyne_xmas_elves/client/exceptions.py
pyne_xmas_elves/server/manage.py
pyne_xmas_elves-0.7.1.data/scripts/elves
pyne_xmas_elves-0.7.1.data/scripts/elves.py
pyne_xmas_elves-0.7.1.dist-info/DESCRIPTION.rst
pyne_xmas_elves-0.7.1.dist-info/METADATA
pyne_xmas_elves-0.7.1.dist-info/RECORD
pyne_xmas_elves-0.7.1.dist-info/WHEEL
pyne_xmas_elves-0.7.1.dist-info/metadata.json
pyne_xmas_elves-0.7.1.dist-info/top_level.txt
server/elves/__init__.py
server/elves/settings.py
server/elves/urls.py
server/elves/wsgi.py
