Metadata-Version: 2.0
Name: pyne-xmas-elves
Version: 0.7.1
Summary: The Great Elf Game adapted for Python North East - client & server
Home-page: http://github.com/pythonnortheast/xmas-elves
Author: Scott Walton
Author-email: scott@pythonnortheast.com
License: MIT
Platform: UNKNOWN
Requires-Dist: asgiref (==1.1.2)
Requires-Dist: asn1crypto (==0.23.0)
Requires-Dist: attrs (==17.2.0)
Requires-Dist: autobahn (==17.10.1)
Requires-Dist: automat (==0.6.0)
Requires-Dist: certifi (==2017.11.5)
Requires-Dist: cffi (==1.11.2)
Requires-Dist: channels (==1.1.8)
Requires-Dist: chardet (==3.0.4)
Requires-Dist: constantly (==15.1.0)
Requires-Dist: coreapi (==2.3.3)
Requires-Dist: coreschema (==0.0.4)
Requires-Dist: coverage (==4.4.2)
Requires-Dist: cryptography (==2.1.4)
Requires-Dist: daphne (==1.3.0)
Requires-Dist: django-filter (==1.1.0)
Requires-Dist: django (==1.11.7)
Requires-Dist: djangorestframework (==3.7.3)
Requires-Dist: docutils (==0.14)
Requires-Dist: hyperlink (==17.3.1)
Requires-Dist: idna (==2.6)
Requires-Dist: incremental (==17.5.0)
Requires-Dist: itypes (==1.1.0)
Requires-Dist: jinja2 (==2.10)
Requires-Dist: m2r (==0.1.12)
Requires-Dist: markupsafe (==1.0)
Requires-Dist: mistune (==0.8.1)
Requires-Dist: pycparser (==2.18)
Requires-Dist: pyopenssl (==17.5.0)
Requires-Dist: pytz (==2017.3)
Requires-Dist: pyyaml (==3.12)
Requires-Dist: requests (==2.18.4)
Requires-Dist: six (==1.11.0)
Requires-Dist: twisted (==17.9.0)
Requires-Dist: txaio (==2.8.2)
Requires-Dist: unittest-xml-reporting (==2.1.0)
Requires-Dist: uritemplate (==3.0.0)
Requires-Dist: urllib3 (==1.22)
Requires-Dist: zope.interface (==4.4.3)
